<class name="Result" table="results">
    <id name="id" column="id">
        <generator class="increment"/>
    </id>
    <property name="x" type="java.lang.Double" column="x"/>
    <property name="y" type="java.lang.Double" column="y"/>
    <property name="r" type="java.lang.Double" column="r"/>
    <property name="query" type="java.lang.Integer" column="query"/>
    <property name="time" type="java.lang.Integer" column="time"/>
    <property name="result" type="java.lang.Boolean" column="result"/>
    <property name="user" type="java.lang.String" column="user"/>
</class>